docstring_format_checker/__init__.py
docstring_format_checker/cli.py
docstring_format_checker/config.py
docstring_format_checker/core.py
docstring_format_checker/utils/__init__.py
docstring_format_checker/utils/exceptions.py
docstring_format_checker-1.11.4.dist-info/WHEEL
docstring_format_checker-1.11.4.dist-info/entry_points.txt
docstring_format_checker-1.11.4.dist-info/METADATA
docstring_format_checker-1.11.4.dist-info/RECORD
