Metadata-Version: 2.4
Name: docstring-format-checker
Version: 1.11.4
Summary: A CLI tool to check and validate Python docstring formatting and completeness
Author: Chris Mahoney
Author-email: Chris Mahoney <docstring-format-checker@data-science-extensions.com>
License-Expression: MIT
Classifier: Development Status :: 5 - Production/Stable
Classifier: License :: OSI Approved :: MIT License
Classifier: Topic :: Software Development :: Quality Assurance
Classifier: Topic :: Software Development :: Libraries :: Python Modules
Classifier: Topic :: Software Development :: Testing :: Unit
Classifier: Topic :: Utilities
Classifier: Programming Language :: Python :: 3
Classifier: Programming Language :: Python :: 3.9
Classifier: Programming Language :: Python :: 3.10
Classifier: Programming Language :: Python :: 3.11
Classifier: Programming Language :: Python :: 3.12
Classifier: Programming Language :: Python :: 3.13
Classifier: Programming Language :: Python :: 3.14
Classifier: Intended Audience :: Developers
Classifier: Environment :: Console
Requires-Dist: typer>=0.9.0
Requires-Dist: tomli>=2.0.0 ; python_full_version < '3.11'
Requires-Dist: rich>=13.0.0
Requires-Dist: toolbox-python==1.*
Requires-Dist: pyfiglet==1.*
Maintainer: Chris Mahoney
Maintainer-email: Chris Mahoney <docstring-format-checker@data-science-extensions.com>
Requires-Python: >=3.9
Project-URL: Changelog, https://data-science-extensions.com/toolboxes/docstring-format-checker/latest/usage/changelog/
Project-URL: Documentation, https://data-science-extensions.com/toolboxes/docstring-format-checker/latest/code/
Project-URL: Homepage, https://data-science-extensions.com/toolboxes/docstring-format-checker
Project-URL: Issues, https://github.com/data-science-extensions/docstring-format-checker/issues
Project-URL: Repository, https://github.com/data-science-extensions/docstring-format-checker
